fileorg/__init__.py
fileorg-67.2.4.dist-info/LICENSE
fileorg-67.2.4.dist-info/METADATA
fileorg-67.2.4.dist-info/WHEEL
fileorg-67.2.4.dist-info/top_level.txt
fileorg-67.2.4.dist-info/RECORD
